sonic_engine
tests
