Metadata-Version: 2.1
Name: sonic-engine
Version: 2.1.15
Summary: Sonic Engine is a python package for the AtlasSonic project
Home-page: UNKNOWN
Author: Soufiane Oualil, Ahmed Bargady
License: UNKNOWN
Platform: UNKNOWN
